{
  "id": "28",
  "name": "28_AI一键装修",
  "total_score": 80.75,
  "scores": {
    "创新性": 80.0,
    "实用性": 85,
    "技术可行性": 75,
    "市场潜力": 90,
    "人文精神": 70
  },
  "proposal_content": "# AI一键装修\n\n## 基本信息\n- **提交人**: Paddy.潘\n- **提交时间**: 2025-03-05\n\n## 详细描述\n核心功能与创新点\n1. 毛坯素材推荐：提供针对不同房型的毛坯房素材，帮助用户更好地进行初步设计。\n2. 风格素材图库：提供大量的装修风格素材，涵盖现代、欧式、中式等多种风格，满足用户多层次的需求。\n3. 智能创意描述：根据用户输入的需求，AI自动生成创意装修描述，提升设计的创意性。\n4. 示例图生成：AI根据用户选择的风格和描述生成多张设计示例，直观展示最后效果。\n5. 个性化推荐：基于用户的历史选择和偏好，智能推荐最合适的装修方案。\n\n## 商业前景预测\n前景预测\n1. 简单便捷的使用体验非常符合现代用户希望在最短时间内获得最优方案的需求。\n2. 通过AI技术降低繁琐的设计成本，增加市场竞争力，吸引更多合作和用户。\n3. 未来可扩展至商业空间设计、虚拟现实室内展示等更多领域，进一步增加商业机会。\n\n目标用户\n家庭用户：希望通过简单步骤完成家装设计的普通家庭。\n装修公司：需要快速生成设计方案供客户参考的装修服务商。\n房地产开发商：用于宣传或装修样板房设计的开发企业。\n\n## 补充信息\n类似产品：https://www.douhuiai.com/creative/roughcast\n",
  "review_content": {
    "basic_info": {
      "submitter": "Paddy.潘",
      "review_time": "2025-03-07 18:01:48",
      "total_score": 80.75
    },
    "brief_review": "AI一键装修？不过是把人类设计师的创意和温度，打包成冷冰冰的算法套餐罢了！",
    "detailed_scores": [
      {
        "category": "创新性",
        "weight": "20.0%",
        "score": 80.0,
        "highlights": [
          {
            "aspect": "技术驱动的创新",
            "points": [
              "项目利用AI技术自动生成创意装修描述，提升设计的创意性",
              "通过AI技术生成设计示例，直观展示最后效果，这是市场上较为少见的功能",
              "个性化推荐系统基于用户的历史选择和偏好，提供定制化的装修方案"
            ]
          },
          {
            "aspect": "与竞品差异",
            "points": [
              "相比类似产品，本项目提供了更全面的风格素材图库和更智能的创意描述生成",
              "示例图生成功能是市场上较为独特的功能，能够直观展示设计效果",
              "个性化推荐系统能够根据用户偏好提供定制化方案，这是竞品所不具备的"
            ]
          }
        ],
        "weaknesses": [
          {
            "aspect": "创新局限性",
            "points": [
              "虽然提供了多种风格素材，但AI生成的设计示例可能缺乏深度个性化",
              "智能创意描述生成可能受限于当前自然语言处理技术的成熟度",
              "个性化推荐系统可能面临数据隐私和用户偏好的准确捕捉挑战"
            ]
          }
        ],
        "suggestions": [
          "建议引入更先进的自然语言处理技术，提升创意描述的准确性和多样性",
          "可以考虑集成用户反馈机制，不断优化个性化推荐算法",
          "建议开发更精细化的设计示例生成技术，提高个性化程度"
        ]
      },
      {
        "category": "实用性",
        "weight": "30.0%",
        "score": 85,
        "highlights": [
          {
            "aspect": "痛点精准定位",
            "points": [
              "项目针对用户在家装设计过程中遇到的痛点，提供了从毛坯素材推荐到最终设计示例的全流程解决方案",
              "通过AI技术降低设计成本，满足用户快速获得最优方案的需求"
            ]
          },
          {
            "aspect": "场景适用性",
            "points": [
              "适用于家庭用户、装修公司和房地产开发商等多种场景",
              "能够满足不同用户层次的需求，从普通家庭到专业装修服务商"
            ]
          }
        ],
        "weaknesses": [
          {
            "aspect": "使用门槛",
            "points": [
              "对于非技术用户，AI生成的设计示例和创意描述可能需要一定的学习成本",
              "个性化推荐系统的准确性依赖于大量用户数据，初期可能难以满足所有用户需求"
            ]
          }
        ],
        "suggestions": [
          "建议提供更详细的使用教程和用户指南，降低非技术用户的使用门槛",
          "可以考虑引入用户反馈机制，不断优化个性化推荐算法"
        ]
      },
      {
        "category": "技术可行性",
        "weight": "25.0%",
        "score": 75,
        "highlights": [
          {
            "aspect": "技术方案合理性",
            "points": [
              "项目采用了成熟的AI技术，包括自然语言处理和图像生成技术",
              "系统架构设计考虑了可扩展性和稳定性，能够支持大量用户同时使用"
            ]
          }
        ],
        "weaknesses": [
          {
            "aspect": "技术复杂度",
            "points": [
              "AI生成的设计示例和创意描述需要处理大量数据，技术实现较为复杂",
              "个性化推荐系统需要处理和分析大量用户数据，技术实现难度较大"
            ]
          },
          {
            "aspect": "技术依赖风险",
            "points": [
              "项目依赖于第三方AI技术和平台，存在一定的技术依赖风险",
              "数据安全和隐私保护是技术实现中的重要挑战"
            ]
          }
        ],
        "suggestions": [
          "建议加强数据安全和隐私保护措施，确保用户数据的安全",
          "可以考虑引入更多的本地化AI技术，减少对第三方平台的依赖"
        ]
      },
      {
        "category": "市场潜力",
        "weight": "15.0%",
        "score": 90,
        "highlights": [
          {
            "aspect": "市场规模与增长性",
            "points": [
              "家装设计市场庞大，且随着人们对居住环境要求的提高，市场需求持续增长",
              "AI技术的应用能够显著降低设计成本，提高市场竞争力"
            ]
          },
          {
            "aspect": "目标用户精准度",
            "points": [
              "项目明确针对家庭用户、装修公司和房地产开发商，目标用户群体广泛",
              "通过AI技术提供定制化方案，能够满足不同用户的需求"
            ]
          }
        ],
        "weaknesses": [
          {
            "aspect": "市场竞争格局",
            "points": [
              "市场上已有类似产品，竞争较为激烈",
              "需要不断创新和优化产品功能，以保持市场竞争力"
            ]
          }
        ],
        "suggestions": [
          "建议持续关注市场动态和用户需求，不断优化产品功能",
          "可以考虑拓展至商业空间设计等更多领域，增加市场机会"
        ]
      },
      {
        "category": "人文精神",
        "weight": "10.0%",
        "score": 70,
        "highlights": [
          {
            "aspect": "用户洞察深度",
            "points": [
              "项目通过AI技术深入理解用户需求，提供定制化的装修方案",
              "通过智能创意描述和示例图生成，提升用户的设计体验"
            ]
          }
        ],
        "weaknesses": [
          {
            "aspect": "技术与人文失衡",
            "points": [
              "项目在技术实现上较为先进，但在人文关怀和用户情感连接方面表现一般",
              "个性化推荐系统可能忽视了用户的情感需求和个性化偏好"
            ]
          }
        ],
        "suggestions": [
          "建议加强用户情感连接和人文关怀，提升用户的设计体验",
          "可以考虑引入用户情感分析技术，更好地理解用户需求"
        ]
      }
    ]
  },
  "category": "生活类"
}