{
  "id": "38",
  "name": "38_多图抠图合并",
  "total_score": 81.0,
  "scores": {
    "创新性": 75.0,
    "实用性": 85,
    "技术可行性": 80,
    "市场潜力": 90,
    "人文精神": 70
  },
  "proposal_content": "# 多图抠图合并\n\n## 基本信息\n- **提交人**: Victor.汪\n- **提交时间**: 2025-03-05\n\n## 详细描述\n场景1：\n将两个不同的图片的人物抠出来，合在一起，可以自定义使用图片1的背景，或者图片二的背景。。\n例如爷爷和孙子，抠出来然后站在一起，类似合照的效果。\n附加延伸：\n图片合成之后，可以让图片动起来，达成gif，或者视频的效果。（很多ai工具已经实现了这个功能）\n\n场景2：\n用户上传两张图片。\n将第一张图片的人物抠出来，使用第二张图片作为背景。\n实现用户的自定义的给人物生成背景的功能。\n\n场景3：\n多张图片上传，人都抠出来合并到一起，实现合照的效果。\n可以使用其中一张图片的背景，作为背景，也可以自定义上传一张新的图片作为背景。\n\n## 商业前景预测\n场景1更适合拉新，做广告会很有效。\n场景2商业价值很大点，因为让用户自主选择自己想要的背景图，听起来效果更好。\n\n\n",
  "review_content": {
    "basic_info": {
      "submitter": "Victor.汪",
      "review_time": "2025-03-07 18:15:45",
      "total_score": 81.0
    },
    "brief_review": "多图合成？不过是给数字时代的\"假合影\"穿上AI外衣，让虚假回忆更具欺骗性罢了！",
    "detailed_scores": [
      {
        "category": "创新性",
        "weight": "20.0%",
        "score": 75.0,
        "highlights": [
          {
            "aspect": "技术驱动的创新",
            "points": [
              "项目通过AI技术实现多图抠图合并，提供了一种新的图片处理方式",
              "支持自定义背景，增加了用户创作的灵活性",
              "延伸功能中提到的将静态图片转化为动态GIF或视频，展示了技术的创新应用"
            ]
          },
          {
            "aspect": "用户体验创新",
            "points": [
              "用户可以通过简单的操作实现复杂的图片合成，降低了使用门槛",
              "提供多种场景应用，满足不同用户的需求"
            ]
          }
        ],
        "weaknesses": [
          {
            "aspect": "创新局限性",
            "points": [
              "市场上已有类似功能的AI工具，如Adobe Photoshop的AI抠图功能",
              "动态图片生成功能虽新颖，但已有多个AI工具实现，如D-ID等"
            ]
          },
          {
            "aspect": "技术依赖",
            "points": [
              "项目可能依赖于先进的图像识别和处理技术，这些技术的稳定性和准确性是关键",
              "动态图片生成功能可能依赖于第三方服务或API，增加了项目的不确定性"
            ]
          }
        ],
        "suggestions": [
          "建议开发独特的图像处理算法，以区别于市场上的现有产品",
          "考虑增加更多创新的图片处理功能，如风格转换、艺术滤镜等，以提升产品的独特价值"
        ]
      },
      {
        "category": "实用性",
        "weight": "30.0%",
        "score": 85,
        "highlights": [
          {
            "aspect": "痛点精准定位",
            "points": [
              "解决了用户想要将多张图片中的人物合成到一张图片中的需求",
              "提供了自定义背景的功能，满足了用户对个性化创作的需求"
            ]
          },
          {
            "aspect": "场景适用性",
            "points": [
              "适用于家庭纪念照、社交媒体内容创作等多种场景",
              "动态图片生成功能适用于制作动态表情包、短视频等"
            ]
          }
        ],
        "weaknesses": [
          {
            "aspect": "使用门槛",
            "points": [
              "对于非专业用户，可能需要一定的学习成本来掌握所有功能",
              "动态图片生成功能可能需要较高的硬件配置，限制了部分用户的使用"
            ]
          }
        ],
        "suggestions": [
          "建议提供详细的使用教程和用户指南，降低用户的学习成本",
          "优化动态图片生成功能的性能，使其能够在更多设备上流畅运行"
        ]
      },
      {
        "category": "技术可行性",
        "weight": "25.0%",
        "score": 80,
        "highlights": [
          {
            "aspect": "技术方案合理性",
            "points": [
              "采用成熟的图像识别和处理技术，技术路线清晰",
              "支持多种图片格式，显示了良好的兼容性"
            ]
          },
          {
            "aspect": "架构设计",
            "points": [
              "模块化设计，便于功能扩展和维护",
              "支持高并发处理，适合大规模用户使用"
            ]
          }
        ],
        "weaknesses": [
          {
            "aspect": "技术复杂度",
            "points": [
              "动态图片生成功能涉及复杂的算法和大量的计算资源",
              "高质量的人物抠图需要精确的图像分割技术，技术难度较高"
            ]
          },
          {
            "aspect": "性能瓶颈",
            "points": [
              "处理高分辨率图片时，可能会遇到性能瓶颈",
              "动态图片生成功能在处理大量数据时，可能会影响系统响应速度"
            ]
          }
        ],
        "suggestions": [
          "建议采用分布式计算技术，提高图片处理的效率和速度",
          "优化图像分割算法，提高抠图的准确性和效率"
        ]
      },
      {
        "category": "市场潜力",
        "weight": "15.0%",
        "score": 90,
        "highlights": [
          {
            "aspect": "市场规模与增长性",
            "points": [
              "随着社交媒体和内容创作的普及，图片处理工具的市场需求持续增长",
              "动态内容创作成为趋势，动态图片生成功能具有较大的市场潜力"
            ]
          },
          {
            "aspect": "目标用户精准度",
            "points": [
              "针对内容创作者、社交媒体用户等有明确需求的用户群体",
              "家庭用户也是重要的目标群体，用于制作家庭纪念照"
            ]
          }
        ],
        "weaknesses": [
          {
            "aspect": "市场竞争格局",
            "points": [
              "市场上已有多个成熟的图片处理工具，如Adobe Photoshop、Canva等",
              "动态图片生成领域也有多个竞争者，如D-ID、Pictory等"
            ]
          }
        ],
        "suggestions": [
          "建议通过差异化定位和特色功能，突出产品的竞争优势",
          "加强与社交媒体平台的合作，扩大产品的市场影响力"
        ]
      },
      {
        "category": "人文精神",
        "weight": "10.0%",
        "score": 70,
        "highlights": [
          {
            "aspect": "用户洞察深度",
            "points": [
              "理解用户对个性化创作的需求，提供了自定义背景的功能",
              "动态图片生成功能满足了用户对动态内容创作的需求"
            ]
          },
          {
            "aspect": "情感连接",
            "points": [
              "通过制作家庭纪念照等功能，增强了用户之间的情感连接",
              "动态表情包等功能增加了社交互动的趣味性"
            ]
          }
        ],
        "weaknesses": [
          {
            "aspect": "表面需求",
            "points": [
              "项目主要满足用户的表面需求，如图片合成和动态内容创作，缺乏更深层次的情感或心理支持"
            ]
          },
          {
            "aspect": "技术与人文失衡",
            "points": [
              "虽然技术功能强大，但在提升用户情感体验和人文关怀方面还有待加强"
            ]
          }
        ],
        "suggestions": [
          "建议增加更多关注用户情感和心理需求的功能，如情绪识别和情感支持",
          "通过用户故事和案例分享，增强产品的人文关怀和情感连接"
        ]
      }
    ]
  },
  "category": "图像类"
}