{
  "id": "55",
  "name": "55_痛车效果制作",
  "total_score": 78.25,
  "scores": {
    "创新性": 75.0,
    "实用性": 80,
    "技术可行性": 70,
    "市场潜力": 85,
    "人文精神": 90
  },
  "proposal_content": "# 痛车效果制作\n\n## 基本信息\n- **提交人**: Wien.文\n- **提交时间**: 2025-03-05\n\n## 详细描述\nACG文化的分支：痛车\n\n对ACGN文化有爱的人们为了彰显个性，将喜爱的动漫角色或者动漫公司或者角色名字之类的字画贴（喷）在车上。以作装饰，被这样装饰过的车子，被称为痛车。痛车未必是汽车。自行车、机车、电动车、车模等都可以用来痛。\n\n是一个低频率、高客单价、定制、非标的业务，大概的流程是【设计>打印>施工】，每个环节都存在较高的溢价。\n\n审批不能传图，有点不太方便，更多内容请看：\nhttps://alidocs.dingtalk.com/i/nodes/kDnRL6jAJMDQMREMc6dzzY37VyMoPYe1?utm_scene=person_space\n\n## 商业前景预测\n也是对已有商业模式在垂直领域的复用（原型设计、Mock up），尽量能让现在这种非标的流程标准化。\n\n市场在国内还处于增量（汽车产业、潮玩等新兴文化产业），主要客群是沿海发达城市、追求个性的年轻人。\n\n",
  "review_content": {
    "basic_info": {
      "submitter": "Wien.文",
      "review_time": "2025-03-07 18:39:07",
      "total_score": 78.25
    },
    "brief_review": "痛车项目巧妙融合二次元文化与汽车个性化,为年轻人提供独特自我表达方式,但标准化流程仍需进一步优化以降低成本、扩大市场。",
    "detailed_scores": [
      {
        "category": "创新性",
        "weight": "20.0%",
        "score": 75.0,
        "highlights": [
          {
            "aspect": "商业模式创新",
            "points": [
              "项目通过标准化流程尝试解决痛车制作中的非标问题，提高效率",
              "针对ACG文化爱好者，提供个性化定制服务，满足特定市场需求"
            ]
          },
          {
            "aspect": "与竞品差异",
            "points": [
              "专注于ACG文化领域，与普通汽车装饰服务形成差异化",
              "提供从设计到施工的一站式服务，简化用户操作流程"
            ]
          }
        ],
        "weaknesses": [
          {
            "aspect": "创新局限性",
            "points": [
              "技术实现依赖于现有的设计和打印技术，创新程度有限",
              "服务流程虽尝试标准化，但仍受限于手工操作，难以完全自动化"
            ]
          },
          {
            "aspect": "模仿风险",
            "points": [
              "商业模式易于模仿，缺乏技术壁垒",
              "市场竞争者可通过类似服务快速进入市场"
            ]
          }
        ],
        "suggestions": [
          "探索引入AR/VR技术，让用户在虚拟环境中预览痛车效果，提升用户体验",
          "开发专属的设计软件或平台，增加技术壁垒，提高模仿难度",
          "与ACG版权方合作，提供官方授权的设计元素，增加服务独特性"
        ]
      },
      {
        "category": "实用性",
        "weight": "30.0%",
        "score": 80,
        "highlights": [
          {
            "aspect": "痛点精准定位",
            "points": [
              "针对ACG文化爱好者对个性化展示的需求，提供定制化解决方案",
              "解决传统痛车制作流程复杂、周期长的问题"
            ]
          },
          {
            "aspect": "场景适用性",
            "points": [
              "适用于汽车、自行车、机车等多种交通工具的装饰",
              "满足展览、聚会等特定场合的个性化需求"
            ]
          }
        ],
        "weaknesses": [
          {
            "aspect": "使用门槛",
            "points": [
              "定制服务价格较高，可能限制部分用户的参与",
              "需要用户具备一定的ACG文化知识，对非爱好者不够友好"
            ]
          },
          {
            "aspect": "场景局限",
            "points": [
              "主要适用于ACG文化相关场景，市场覆盖面有限",
              "对于非ACG文化爱好者，服务吸引力不足"
            ]
          }
        ],
        "suggestions": [
          "推出不同价格区间的服务套餐，扩大用户覆盖面",
          "增加对非ACG文化爱好者的引导和教育，扩大市场基础",
          "开发易于操作的设计工具，降低用户参与门槛"
        ]
      },
      {
        "category": "技术可行性",
        "weight": "25.0%",
        "score": 70,
        "highlights": [
          {
            "aspect": "技术方案合理性",
            "points": [
              "采用成熟的设计和打印技术，确保服务质量和效率",
              "流程标准化尝试，有助于提高服务的一致性和可靠性"
            ]
          }
        ],
        "weaknesses": [
          {
            "aspect": "技术复杂度",
            "points": [
              "个性化设计需求可能导致技术实现复杂，增加成本",
              "手工施工环节难以完全自动化，影响效率"
            ]
          },
          {
            "aspect": "技术依赖风险",
            "points": [
              "依赖于第三方设计和打印技术，存在供应链风险",
              "技术更新可能带来额外的适应成本"
            ]
          }
        ],
        "suggestions": [
          "探索自动化施工技术，提高效率和降低成本",
          "建立稳定的供应链合作关系，减少技术依赖风险",
          "持续关注行业技术发展，及时更新服务流程和技术"
        ]
      },
      {
        "category": "市场潜力",
        "weight": "15.0%",
        "score": 85,
        "highlights": [
          {
            "aspect": "市场规模与增长性",
            "points": [
              "ACG文化市场持续增长，痛车作为其分支具有较大发展潜力",
              "随着个性化消费趋势的增强，痛车服务的市场需求有望增加"
            ]
          },
          {
            "aspect": "目标用户精准度",
            "points": [
              "主要面向沿海发达城市的年轻人群，与ACG文化爱好者高度重合",
              "针对追求个性化的用户群体，市场定位明确"
            ]
          }
        ],
        "weaknesses": [
          {
            "aspect": "市场竞争格局",
            "points": [
              "市场上存在多家痛车服务提供商，竞争激烈",
              "新进入者可能通过价格战等方式快速抢占市场份额"
            ]
          },
          {
            "aspect": "获客挑战",
            "points": [
              "ACG文化爱好者群体相对集中，市场拓展空间有限",
              "需要投入较多资源进行市场教育和品牌建设"
            ]
          }
        ],
        "suggestions": [
          "加强品牌建设，提升品牌知名度和用户忠诚度",
          "探索跨界合作，扩大服务应用场景和用户基础",
          "利用社交媒体和ACG社区进行精准营销，提高获客效率"
        ]
      },
      {
        "category": "人文精神",
        "weight": "10.0%",
        "score": 90,
        "highlights": [
          {
            "aspect": "用户洞察深度",
            "points": [
              "深入理解ACG文化爱好者的个性化展示需求，提供定制化服务",
              "通过痛车制作，满足用户对ACG文化的热爱和表达"
            ]
          },
          {
            "aspect": "情感连接",
            "points": [
              "痛车作为ACG文化的载体，能够与用户建立深厚的情感连接",
              "通过个性化设计，增强用户对作品的认同感和归属感"
            ]
          }
        ],
        "weaknesses": [
          {
            "aspect": "表面需求",
            "points": [
              "服务主要满足用户的个性化展示需求，对深层次需求的挖掘不足",
              "缺乏对用户心理和行为的深入分析，服务深度有待提升"
            ]
          }
        ],
        "suggestions": [
          "开展用户研究，深入了解ACG文化爱好者的深层次需求和心理",
          "开发更多与ACG文化相关的增值服务，增强用户粘性",
          "建立用户社区，促进用户之间的交流和分享，增强归属感"
        ]
      }
    ]
  },
  "category": "图像类"
}